README.rst
setup.py
telebot7/__init__.py
telebot7/long_polling.py
telebot7/telebot.py
telebot7.egg-info/PKG-INFO
telebot7.egg-info/SOURCES.txt
telebot7.egg-info/dependency_links.txt
telebot7.egg-info/requires.txt
telebot7.egg-info/top_level.txt