Metadata-Version: 1.1
Name: telebot7
Version: 0.1
Summary: Telegram Bot API Python wrapper.
Home-page: https://github.com/pash4paul/telebot7
Author: Pavel Fomin
Author-email: pash4paul@gmail.com
License: UNKNOWN
Keywords: telegram bot api
Platform: UNKNOWN
Classifier: Development Status :: 3 - Alpha
Classifier: Environment :: Console
Classifier: Intended Audience :: Developers
Classifier: Intended Audience :: Science/Research
Classifier: License :: OSI Approved :: MIT License
Classifier: Programming Language :: Python :: 3
Classifier: Programming Language :: Python :: 3.4
Classifier: Programming Language :: Python :: 3.5
Classifier: Programming Language :: Python :: 3.6
Classifier: Topic :: Software Development :: Libraries :: Python Modules
